unigram/__init__.py
unigram/assets/fol_nli_axioms
unigram/assets/fol_nli_verbalization.py
unigram/generate.py
unigram/generate_recursive.py
unigram/generate_sequential.py
unigram/grammar.py
unigram/grammars/FOL.py
unigram/grammars/__init__.py
unigram/grammars/english.py
unigram/grammars/tinypy.py
unigram/solver_utils/tptp.py
unigram-0.15.2.dist-info/METADATA
unigram-0.15.2.dist-info/WHEEL
unigram-0.15.2.dist-info/licenses/LICENSE
unigram-0.15.2.dist-info/RECORD
