Metadata-Version: 2.4
Name: unigram
Version: 0.15.2
Summary: 
License: MIT
License-File: LICENSE
Author: Damien Sileo
Requires-Python: >=3.7,<4.0
Classifier: License :: OSI Approved :: MIT License
Classifier: Programming Language :: Python :: 3
Classifier: Programming Language :: Python :: 3.7
Classifier: Programming Language :: Python :: 3.8
Classifier: Programming Language :: Python :: 3.9
Classifier: Programming Language :: Python :: 3.10
Classifier: Programming Language :: Python :: 3.11
Classifier: Programming Language :: Python :: 3.12
Classifier: Programming Language :: Python :: 3.13
Classifier: Programming Language :: Python :: 3.14
Requires-Dist: anytree (>=2,<3)
Requires-Dist: exrex
Requires-Dist: funcy
Requires-Dist: networkx
